{
  "generated_at": "2026-04-10T11:08:31.491731",
  "hive": {
    "all_ok": true,
    "bee_count": 5,
    "bees_detail": {
      "dancer": {
        "name": "dancer",
        "state": "ready",
        "trigger_type": "event",
        "last_run": null,
        "last_run_duration": null,
        "total_runs": 0,
        "error_count": 0,
        "consecutive_errors": 0,
        "ok": true
      },
      "guard": {
        "name": "guard",
        "state": "ready",
        "trigger_type": "event",
        "last_run": null,
        "last_run_duration": null,
        "total_runs": 0,
        "error_count": 0,
        "consecutive_errors": 0,
        "ok": true
      },
      "scout": {
        "name": "scout",
        "state": "ready",
        "trigger_type": "cron",
        "last_run": "2026-04-10T11:08:30.518124",
        "last_run_duration": null,
        "total_runs": 1,
        "error_count": 0,
        "consecutive_errors": 0,
        "ok": true
      },
      "nurse": {
        "name": "nurse",
        "state": "ready",
        "trigger_type": "cron",
        "last_run": null,
        "last_run_duration": null,
        "total_runs": 0,
        "error_count": 0,
        "consecutive_errors": 0,
        "ok": true
      },
      "builder": {
        "name": "builder",
        "state": "ready",
        "trigger_type": "event",
        "last_run": null,
        "last_run_duration": null,
        "total_runs": 0,
        "error_count": 0,
        "consecutive_errors": 0,
        "ok": true
      }
    },
    "state": {
      "mode": "normal",
      "mode_params": {},
      "mode_set_at": "2026-03-21T17:29:20.236074",
      "mode_expires_at": null,
      "family_overrides": {}
    }
  },
  "bees": {},
  "events": {
    "total": 1270,
    "recent_500": 500,
    "today": 62,
    "by_type": {
      "feishu_sent": 368,
      "scene_report": 132
    },
    "by_source": {
      "dancer": 368,
      "scout": 132
    },
    "last_10": [
      {
        "source": "dancer",
        "type": "feishu_sent",
        "intensity": "normal",
        "payload": {
          "text": "帧差无变化，家里一切正常",
          "target": "ou_a9ca7506b002b1be36148b97d622d551"
        },
        "dance": "waggle",
        "timestamp": "2026-04-10T11:08:31.308629"
      },
      {
        "source": "dancer",
        "type": "feishu_sent",
        "intensity": "normal",
        "payload": {
          "text": "帧差无变化，家里一切正常",
          "target": "ou_a9ca7506b002b1be36148b97d622d551"
        },
        "dance": "waggle",
        "timestamp": "2026-04-10T11:03:27.608057"
      },
      {
        "source": "dancer",
        "type": "feishu_sent",
        "intensity": "normal",
        "payload": {
          "text": "帧差无变化，家里一切正常",
          "target": "ou_a9ca7506b002b1be36148b97d622d551"
        },
        "dance": "waggle",
        "timestamp": "2026-04-10T10:58:24.245017"
      },
      {
        "source": "dancer",
        "type": "feishu_sent",
        "intensity": "normal",
        "payload": {
          "text": "帧差无变化，家里一切正常",
          "target": "ou_a9ca7506b002b1be36148b97d622d551"
        },
        "dance": "waggle",
        "timestamp": "2026-04-10T10:53:20.656936"
      },
      {
        "source": "scout",
        "type": "scene_report",
        "intensity": "normal",
        "payload": {
          "report": "【在家人员】  \nPERSON_FEATURE: 短发男性，深灰连帽衫+黑色短裤+拖鞋，正弯腰整理墙角物品 | GUESS: 晓峰（⚠️时间异常：周五08:57应为工作日，晓峰通常不在家，需核实是否临时回家）\n\n【状态评估】  \n动作正常，无异常行为，疑似整理杂物。\n\n【环境检查】  \n室温21°C/湿度64-66%，舒适；室外晴19.5°C，无风雨，无需调整空调或关窗。\n\n【提醒事项】  \n⚠️晓峰出现在非预期时间（工作日早9点），建议确认是否临时居家办公。17:00姥姥需接小宝，距今尚早，暂不提醒。\n\n【建议】  \n确认晓峰是否在家办公，避免误判。保持客厅整洁，避免杂物绊倒小宝。",
          "image_path": "/tmp/home_patrol_snapshot.jpg"
        },
        "dance": "waggle",
        "timestamp": "2026-04-10T10:48:15.372232"
      },
      {
        "source": "dancer",
        "type": "feishu_sent",
        "intensity": "normal",
        "payload": {
          "text": "帧差无变化，家里一切正常",
          "target": "ou_a9ca7506b002b1be36148b97d622d551"
        },
        "dance": "waggle",
        "timestamp": "2026-04-10T10:43:08.458794"
      },
      {
        "source": "dancer",
        "type": "feishu_sent",
        "intensity": "normal",
        "payload": {
          "text": "帧差无变化，家里一切正常",
          "target": "ou_a9ca7506b002b1be36148b97d622d551"
        },
        "dance": "waggle",
        "timestamp": "2026-04-10T10:38:05.406534"
      },
      {
        "source": "dancer",
        "type": "feishu_sent",
        "intensity": "normal",
        "payload": {
          "text": "帧差无变化，家里一切正常",
          "target": "ou_a9ca7506b002b1be36148b97d622d551"
        },
        "dance": "waggle",
        "timestamp": "2026-04-10T10:33:01.298912"
      },
      {
        "source": "dancer",
        "type": "feishu_sent",
        "intensity": "normal",
        "payload": {
          "text": "帧差无变化，家里一切正常",
          "target": "ou_a9ca7506b002b1be36148b97d622d551"
        },
        "dance": "waggle",
        "timestamp": "2026-04-10T10:27:58.054815"
      },
      {
        "source": "dancer",
        "type": "feishu_sent",
        "intensity": "normal",
        "payload": {
          "text": "帧差无变化，家里一切正常",
          "target": "ou_a9ca7506b002b1be36148b97d622d551"
        },
        "dance": "waggle",
        "timestamp": "2026-04-10T10:22:53.691706"
      }
    ]
  },
  "family": {
    "today_sightings": {},
    "week_sightings": {},
    "daily_activity": {}
  },
  "system": {
    "log_size_kb": 57.7,
    "brain": {
      "known_people": 8,
      "learning_people": 20,
      "habits_discovered": 1,
      "total_observations": 0,
      "log_entries": 1099,
      "devices": 117,
      "last_device_scan": "2026-03-18T14:03:22.095522"
    },
    "last_patrol_lines": [
      "   ✅ guard: ready (跑了0次)",
      "   ✅ scout: ready (跑了1次)",
      "   ✅ nurse: ready (跑了0次)",
      "   ✅ builder: ready (跑了0次)",
      "[2026-04-10 11:03:28] [hive.queen] [info] run_all 完成，全部正常"
    ],
    "uptime_note": "LaunchAgent 每5分钟触发"
  },
  "patrol_timeline": [
    {
      "time": "2026-04-10 09:31:04",
      "level": "info",
      "msg": "开始巡查..."
    },
    {
      "time": "2026-04-10 09:36:09",
      "level": "info",
      "msg": "开始巡查..."
    },
    {
      "time": "2026-04-10 09:41:28",
      "level": "info",
      "msg": "开始巡查..."
    },
    {
      "time": "2026-04-10 09:46:33",
      "level": "info",
      "msg": "开始巡查..."
    },
    {
      "time": "2026-04-10 09:51:37",
      "level": "info",
      "msg": "开始巡查..."
    },
    {
      "time": "2026-04-10 09:56:41",
      "level": "info",
      "msg": "开始巡查..."
    },
    {
      "time": "2026-04-10 10:01:45",
      "level": "info",
      "msg": "开始巡查..."
    },
    {
      "time": "2026-04-10 10:06:49",
      "level": "info",
      "msg": "开始巡查..."
    },
    {
      "time": "2026-04-10 10:12:41",
      "level": "info",
      "msg": "开始巡查..."
    },
    {
      "time": "2026-04-10 10:17:48",
      "level": "info",
      "msg": "开始巡查..."
    },
    {
      "time": "2026-04-10 10:22:51",
      "level": "info",
      "msg": "开始巡查..."
    },
    {
      "time": "2026-04-10 10:27:56",
      "level": "info",
      "msg": "开始巡查..."
    },
    {
      "time": "2026-04-10 10:32:59",
      "level": "info",
      "msg": "开始巡查..."
    },
    {
      "time": "2026-04-10 10:38:03",
      "level": "info",
      "msg": "开始巡查..."
    },
    {
      "time": "2026-04-10 10:43:06",
      "level": "info",
      "msg": "开始巡查..."
    },
    {
      "time": "2026-04-10 10:48:10",
      "level": "info",
      "msg": "开始巡查..."
    },
    {
      "time": "2026-04-10 10:53:18",
      "level": "info",
      "msg": "开始巡查..."
    },
    {
      "time": "2026-04-10 10:58:22",
      "level": "info",
      "msg": "开始巡查..."
    },
    {
      "time": "2026-04-10 11:03:25",
      "level": "info",
      "msg": "开始巡查..."
    },
    {
      "time": "2026-04-10 11:08:29",
      "level": "info",
      "msg": "开始巡查..."
    }
  ],
  "error_trend": {},
  "honey": [
    {
      "name": "weekly_2026-03-21.md",
      "size": 497
    },
    {
      "name": "monthly_2026-03.md",
      "size": 1502
    }
  ]
}